hsa_elastica/__init__.py
hsa_elastica/boundary_conditions/__init__.py
hsa_elastica/boundary_conditions/hsa_motor_controlled_rot_bc.py
hsa_elastica/boundary_conditions/hsa_motor_free_rot_bc.py
hsa_elastica/callbacks/__init__.py
hsa_elastica/callbacks/hsa_diagnostic_callbacks.py
hsa_elastica/dissipation/__init__.py
hsa_elastica/dissipation/configurable_analytical_linear_damper.py
hsa_elastica/forcing/__init__.py
hsa_elastica/forcing/local_endpoint_forces.py
hsa_elastica/forcing/proximal_end_torque.py
hsa_elastica/memory_block/__init__.py
hsa_elastica/memory_block/memory_block_hsa_rod.py
hsa_elastica/modules/__init__.py
hsa_elastica/modules/base_system.py
hsa_elastica/modules/memory_block.py
hsa_elastica/rod/__init__.py
hsa_elastica/rod/factory_function.py
hsa_elastica/rod/hsa_rod.py
hsa_elastica/simulation/__init__.py
hsa_elastica/simulation/hsa_robot_simulator.py
hsa_elastica/simulation/hsa_rod_simulator.py
hsa_elastica/utils/__init__.py
hsa_elastica/utils/check_freq_activation.py
hsa_elastica/utils/data_mapping_utils.py
hsa_elastica/utils/load_diagnostic_data.py
hsa_pyelastica-0.0.1.dist-info/LICENSE
hsa_pyelastica-0.0.1.dist-info/METADATA
hsa_pyelastica-0.0.1.dist-info/WHEEL
hsa_pyelastica-0.0.1.dist-info/top_level.txt
hsa_pyelastica-0.0.1.dist-info/RECORD
