Metadata-Version: 2.1
Name: hsa-pyelastica
Version: 0.0.1
Summary: A plugin to PyElastica for the simulation of robots based on Handed Shearing Auxetics (HSAs).
Author-email: Maximilian Stölzle <maximilian@stoelzle.ch>
License: MIT
Project-URL: Homepage, https://github.com/tud-cor-sr/HSA-PyElastica
Project-URL: Bug Tracker, https://github.com/tud-cor-sr/HSA-PyElastica/issues
Classifier: Development Status :: 3 - Alpha
Classifier: Intended Audience :: Developers
Classifier: Topic :: Software Development :: Build Tools
Classifier: License :: OSI Approved :: MIT License
Classifier: Programming Language :: Python :: 3
Classifier: Programming Language :: Python :: 3.8
Classifier: Programming Language :: Python :: 3.9
Classifier: Programming Language :: Python :: 3.10
Classifier: Programming Language :: Python :: 3.11
Classifier: Programming Language :: Python :: 3 :: Only
Requires-Python: >=3.8
License-File: LICENSE
Requires-Dist: numpy
Requires-Dist: progressbar2
Requires-Dist: pyelastica (==0.3.0)
Requires-Dist: PyYAML
Requires-Dist: requests
Provides-Extra: dev
Requires-Dist: black ; extra == 'dev'
Requires-Dist: bump2version ; extra == 'dev'
Requires-Dist: codecov ; extra == 'dev'
Requires-Dist: coverage ; extra == 'dev'
Requires-Dist: pre-commit ; extra == 'dev'
Requires-Dist: pytest ; extra == 'dev'
Requires-Dist: pytest-cov ; extra == 'dev'
Requires-Dist: pytest-html ; extra == 'dev'
Requires-Dist: tox ; extra == 'dev'
Provides-Extra: examples
Requires-Dist: matplotlib ; extra == 'examples'
Requires-Dist: pycairo ; extra == 'examples'
Requires-Dist: pyvista ; extra == 'examples'
Requires-Dist: seaborn ; extra == 'examples'
